{"type":"FeatureCollection","name":"PS","crs":{"type":"name","properties":{"name":"urn:ogc:def:crs:OGC:1.3:CRS84"}},"bbox":[34.200269441306,31.2114489580001,35.572536255,32.542640076],"features":[{"type":"Feature","properties":{"timezone":"Asia/Hebron"},"bbox":[34.8672,31.3449,35.5725,32.5426],"geometry":{"type":"MultiPolygon","coordinates":[[[[34.8672,31.3449],[34.8672,32.5426],[35.5725,32.5426],[35.5725,31.3449],[34.8672,31.3449]]]]}},{"type":"Feature","properties":{"timezone":"Asia/Gaza"},"bbox":[34.2003,31.2114,34.556,31.5831],"geometry":{"type":"MultiPolygon","coordinates":[[[[34.2003,31.2114],[34.2003,31.5831],[34.556,31.5831],[34.556,31.2114],[34.2003,31.2114]]]]}}]}